PYB11Generator/PYB11ClassAttribute.py
PYB11Generator/PYB11Decorators.py
PYB11Generator/PYB11Publicist.py
PYB11Generator/PYB11STLmethods.py
PYB11Generator/PYB11Trampoline.py
PYB11Generator/PYB11attr.py
PYB11Generator/PYB11class.py
PYB11Generator/PYB11config.py
PYB11Generator/PYB11enum.py
PYB11Generator/PYB11function.py
PYB11Generator/PYB11property.py
PYB11Generator/PYB11utils.py
PYB11Generator/__init__.py
pyb11generator-2025.12.1.dist-info/licenses/LICENSE
pyb11generator-2025.12.1.dist-info/licenses/NOTICE
pyb11generator-2025.12.1.dist-info/METADATA
pyb11generator-2025.12.1.dist-info/WHEEL
pyb11generator-2025.12.1.dist-info/top_level.txt
pyb11generator-2025.12.1.dist-info/RECORD
