Metadata-Version: 2.4
Name: PYB11Generator
Version: 2025.12.1
Summary: PYB11Generator is a code generation tool which generates pybind11 code for binding C++ to Python. Documentation is available at https://pyb11generator.readthedocs.io/
Author-email: "J. Michael Owen" <mikeowen@llnl.gov>
License-Expression: BSD-3-Clause
Project-URL: Homepage, https://github.com/LLNL/PYB11Generator
Project-URL: Bug Tracker, https://github.com/LLNL/PYB11Generator/issues
Classifier: Programming Language :: Python :: 3
Classifier: Operating System :: OS Independent
Requires-Python: >=3.8
License-File: LICENSE
License-File: NOTICE
Requires-Dist: pybind11>3.0.0
Dynamic: license-file
